bsv/__init__.py
bsv/constant.py
bsv/downloader.py
bsv-0.6.dist-info/LICENSE
bsv-0.6.dist-info/METADATA
bsv-0.6.dist-info/WHEEL
bsv-0.6.dist-info/top_level.txt
bsv-0.6.dist-info/RECORD
